<DOC>
<DOCNO>1</DOCNO>CNN International - Breaking News, US News, World News and Video</DOC>
<DOC>
<DOCNO>2</DOCNO>Tech News - Latest Technology Headlines and Trends on CNN Business - CNN</DOC>
<DOC>
<DOCNO>3</DOCNO>آخر الأخبار السياسية والاقتصادية والرياضية والفنية وأحدث تقارير الفيديو - CNN Arabic</DOC>
<DOC>
<DOCNO>4</DOCNO>Election 101 - CNN</DOC>
<DOC>
<DOCNO>5</DOCNO>China news - breaking news, video, headlines and opinion - CNN</DOC>
<DOC>
<DOCNO>6</DOCNO>CNN Longform - CNN</DOC>
<DOC>
<DOCNO>7</DOCNO>Wildfire map and air quality tracker</DOC>
<DOC>
<DOCNO>8</DOCNO>Destinations | CNN Travel</DOC>
<DOC>
<DOCNO>9</DOCNO>Places to Stay | CNN Travel</DOC>
<DOC>
<DOCNO>10</DOCNO>Foreseeable Future - CNN</DOC>
<DOC>
<DOCNO>11</DOCNO>Mission: Ahead - CNN</DOC>
<DOC>
<DOCNO>12</DOCNO>Luxury goods, precious gems and high end spending - CNN Style</DOC>
<DOC>
<DOCNO>13</DOCNO>Media News - Latest Headlines on CNN Business - CNN</DOC>
<DOC>
<DOCNO>14</DOCNO>Stock Market Data - Dow Jones, Nasdaq, S&amp;P 500 - CNNMoney</DOC>
<DOC>
<DOCNO>15</DOCNO>Asia news - breaking news, video, headlines and opinion - CNN</DOC>
<DOC>
<DOCNO>16</DOCNO>Google</DOC>
<DOC>
<DOCNO>17</DOCNO>TV Shows - Entertainment News - CNN</DOC>
<DOC>
<DOCNO>18</DOCNO>Celebrities - Entertainment News - CNN</DOC>
<DOC>
<DOCNO>19</DOCNO>rubiconproject.com</DOC>
<DOC>
<DOCNO>20</DOCNO>Fitness and Exercise - CNN</DOC>
<DOC>
<DOCNO>21</DOCNO>CNN Profiles - CNN</DOC>
<DOC>
<DOCNO>22</DOCNO>Design - CNN Style</DOC>
<DOC>
<DOCNO>23</DOCNO>Analysis – CNN Business - CNN</DOC>
<DOC>
<DOCNO>24</DOCNO>CNNPolitics - Political News, Analysis and Opinion</DOC>
<DOC>
<DOCNO>25</DOCNO>Impact Your World  - CNN</DOC>
<DOC>
<DOCNO>26</DOCNO>Inside Africa - CNN</DOC>
<DOC>
<DOCNO>27</DOCNO>Show jumping news, equestrian sports and horse shows - CNN</DOC>
<DOC>
<DOCNO>28</DOCNO>Climate change: Latest news and explainers - CNN</DOC>
<DOC>
<DOCNO>29</DOCNO>Travel News | CNN Travel</DOC>
<DOC>
<DOCNO>30</DOCNO>Skiing news, videos, interviews and features - CNN</DOC>
<DOC>
<DOCNO>31</DOCNO>Pop Culture - Entertainment News - CNN</DOC>
<DOC>
<DOCNO>32</DOCNO>CNN en Español | Últimas noticias en español de Latinoamérica, Estados Unidos y el mundo</DOC>
<DOC>
<DOCNO>33</DOCNO>Breaking News, Latest News and Videos - CNN</DOC>
<DOC>
<DOCNO>34</DOCNO>CNN TV Schedule - CNN</DOC>
<DOC>
<DOCNO>35</DOCNO>Architecture news and features from around the world - CNN Style</DOC>
<DOC>
<DOCNO>36</DOCNO>CNN Style - Fashion, beauty, design, art, architecture and luxury</DOC>
<DOC>
<DOCNO>37</DOCNO>Food and Diet - CNN</DOC>
<DOC>
<DOCNO>38</DOCNO>Weather video - CNN</DOC>
<DOC>
<DOCNO>39</DOCNO>CNN Investigates - CNN</DOC>
<DOC>
<DOCNO>40</DOCNO>Latest tennis news, headlines, videos and analysis - CNN</DOC>
<DOC>
<DOCNO>41</DOCNO>Art news, features and art events around the world - CNN Style</DOC>
<DOC>
<DOCNO>42</DOCNO>Digital Studios - CNN</DOC>
<DOC>
<DOCNO>43</DOCNO>Middle East news - breaking news, video, headlines and opinion - CNN</DOC>
<DOC>
<DOCNO>44</DOCNO>Australia news - breaking news, video, headlines and opinion - CNN</DOC>
<DOC>
<DOCNO>45</DOCNO>Football news, headlines, videos, interviews and comment - CNN</DOC>
<DOC>
<DOCNO>46</DOCNO>CNN Profiles - CNN</DOC>
<DOC>
<DOCNO>47</DOCNO>India news - breaking news, video, headlines and opinion - CNN</DOC>
<DOC>
<DOCNO>48</DOCNO>Climate change: The importance of 2 degrees - CNN</DOC>
<DOC>
<DOCNO>49</DOCNO>CNN Heroes: Everyday people changing the world - CNN</DOC>
<DOC>
<DOCNO>50</DOCNO>Golf news, headlines, latest videos and analysis - CNN</DOC>
<DOC>
<DOCNO>51</DOCNO>Formula 1 news, results, videos and features - CNN</DOC>
<DOC>
<DOCNO>52</DOCNO>Horse racing news, headlines, interviews and features - CNN</DOC>
<DOC>
<DOCNO>53</DOCNO>Fashion news and features and the latest on celebrity fashion - CNN Style</DOC>
<DOC>
<DOCNO>54</DOCNO>CNN Digital Shorts - CNN</DOC>
<DOC>
<DOCNO>55</DOCNO>Videos - CNN Business - CNN</DOC>
<DOC>
<DOCNO>56</DOCNO>Parenting - CNN</DOC>
<DOC>
<DOCNO>57</DOCNO>Special Features - CNN</DOC>
<DOC>
<DOCNO>58</DOCNO>World news – breaking news, videos and headlines - CNN</DOC>
<DOC>
<DOCNO>59</DOCNO>Fact Check - CNN</DOC>
<DOC>
<DOCNO>60</DOCNO>Travel Videos | CNN Travel</DOC>
<DOC>
<DOCNO>61</DOCNO>Beauty news and features around the world - CNN Style</DOC>
<DOC>
<DOCNO>62</DOCNO>CNN Photos - CNN</DOC>
<DOC>
<DOCNO>63</DOCNO>Upstarts - CNN</DOC>
<DOC>
<DOCNO>64</DOCNO>Latest sports news, videos, interviews and comment - CNN</DOC>
<DOC>
<DOCNO>65</DOCNO>Esports - CNN</DOC>
<DOC>
<DOCNO>66</DOCNO>Health News - CNN</DOC>
<DOC>
<DOCNO>67</DOCNO>Innovative Cities - CNN</DOC>
<DOC>
<DOCNO>68</DOCNO>Africa news - breaking news, video, headlines and opinion - CNN</DOC>
<DOC>
<DOCNO>69</DOCNO>Gadget - CNN</DOC>
<DOC>
<DOCNO>70</DOCNO>Americas news - breaking news, video, headlines and opinion - CNN</DOC>
<DOC>
<DOCNO>71</DOCNO>CNN - Breaking News, Latest News and Videos</DOC>
<DOC>
<DOCNO>72</DOCNO>CNN Travel | Global Destinations, Tips &amp; Video</DOC>
<DOC>
<DOCNO>73</DOCNO>UK news - breaking news, video, headlines and opinion - CNN</DOC>
<DOC>
<DOCNO>74</DOCNO>Vital Signs with Dr. Sanjay Gupta - CNN</DOC>
<DOC>
<DOCNO>75</DOCNO>Videos - CNN Style</DOC>
<DOC>
<DOCNO>76</DOCNO>Food &amp; Drink | CNN Travel</DOC>
<DOC>
<DOCNO>77</DOCNO>Careers - News for Entrepreneurs and Leaders on CNN Business - CNN</DOC>
<DOC>
<DOCNO>78</DOCNO>Entertainment News - Celebrities, Movies, TV, Music - CNN</DOC>
<DOC>
<DOCNO>79</DOCNO>Virtual Reality &amp; 360° Video - CNNVR - CNN</DOC>
<DOC>
<DOCNO>80</DOCNO>Video News - CNN</DOC>
<DOC>
<DOCNO>81</DOCNO>CNN TV Shows - CNN</DOC>
<DOC>
<DOCNO>82</DOCNO>CNN International - Breaking News, US News, World News and Video</DOC>
<DOC>
<DOCNO>83</DOCNO>Wellness - CNN</DOC>
<DOC>
<DOCNO>84</DOCNO>Breaking News, Latest News and Videos - CNN</DOC>
<DOC>
<DOCNO>85</DOCNO>Formula E news, videos, features and interviews - CNN</DOC>
<DOC>
<DOCNO>86</DOCNO>HLN - CNN</DOC>
<DOC>
<DOCNO>87</DOCNO>Weather news and local forecast - CNN</DOC>
<DOC>
<DOCNO>88</DOCNO>CNN newsletters: Subscribe for news, lifestyle, markets info and more</DOC>
<DOC>
<DOCNO>89</DOCNO>Movies - Entertainment News - CNN</DOC>
<DOC>
<DOCNO>90</DOCNO>Europe news - breaking news, video, headlines and opinion - CNN</DOC>
<DOC>
<DOCNO>91</DOCNO>Innovate - CNN</DOC>
<DOC>
<DOCNO>92</DOCNO>The CNN Freedom Project — ending modern-day slavery</DOC>
<DOC>
<DOCNO>93</DOCNO>Snowstorm tracker: Follow the storm's path</DOC>
<DOC>
<DOCNO>94</DOCNO>Presidential Election Results and Electoral Map 2020</DOC>
<DOC>
<DOCNO>95</DOCNO>Work Transformed - CNN</DOC>
<DOC>
<DOCNO>96</DOCNO>පුරනය වන්න - Google ගිණුම්</DOC>
<DOC>
<DOCNO>97</DOCNO>Search our Job Opportunities at WarnerMedia</DOC>
<DOC>
<DOCNO>98</DOCNO>Call to Earth</DOC>
<DOC>
<DOCNO>99</DOCNO>CNNgo – Watch CNN TV live</DOC>